timetagger/__init__.py
timetagger/__main__.py
timetagger/_config.py
timetagger/app/__init__.py
timetagger/app/_template.html
timetagger/app/app.scss
timetagger/app/demo.md
timetagger/app/dialogs.py
timetagger/app/dt.py
timetagger/app/front.py
timetagger/app/index.md
timetagger/app/jspdf.js
timetagger/app/sandbox.md
timetagger/app/stores.py
timetagger/app/sw.js
timetagger/app/timetagger_manifest.json
timetagger/app/tools.py
timetagger/app/utils.py
timetagger/common/SpaceMono-Regular-webfont.woff
timetagger/common/Ubuntu-C-normal.js
timetagger/common/Ubuntu-C.ttf
timetagger/common/Ubuntu-R-normal.js
timetagger/common/Ubuntu-R.ttf
timetagger/common/UbuntuCondensed_latin.woff2
timetagger/common/Ubuntu_latin.woff2
timetagger/common/__init__.py
timetagger/common/_style_embed.scss
timetagger/common/_template.html
timetagger/common/bcrypt.js
timetagger/common/clearly-602.ogg
timetagger/common/cred.html
timetagger/common/eventually-590.ogg
timetagger/common/fa-solid-900.woff2
timetagger/common/sha1.html
timetagger/common/wind-up-1-534.ogg
timetagger/images/__init__.py
timetagger/images/_names.txt
timetagger/images/_update_icons.py
timetagger/images/_update_paper.py
timetagger/images/favicon.ico
timetagger/images/paper0.jpg
timetagger/images/paper1.jpg
timetagger/images/paper2.jpg
timetagger/images/paper3.jpg
timetagger/images/timetagger128_sf.png
timetagger/images/timetagger16_sf.png
timetagger/images/timetagger192_bd.png
timetagger/images/timetagger192_sd.png
timetagger/images/timetagger192_sf.png
timetagger/images/timetagger192_sf_dot.png
timetagger/images/timetagger192_sl.png
timetagger/images/timetagger192_sm.png
timetagger/images/timetagger192_tg.png
timetagger/images/timetagger256_sf.png
timetagger/images/timetagger32_sf.png
timetagger/images/timetagger48_sf.png
timetagger/images/timetagger512_bd.png
timetagger/images/timetagger512_sf.png
timetagger/images/timetagger512_sm.png
timetagger/images/timetagger64_sf.png
timetagger/images/timetagger_sd.svg
timetagger-26.1.1.dist-info/licenses/LICENSE
timetagger-26.1.1.dist-info/METADATA
timetagger-26.1.1.dist-info/WHEEL
timetagger-26.1.1.dist-info/top_level.txt
timetagger-26.1.1.dist-info/RECORD
