Metadata-Version: 2.4
Name: timetagger
Version: 26.1.1
Summary: Tag your time, get the insight - an open source time tracker for individuals
Home-page: https://github.com/almarklein/timetagger
Author: Almar Klein
Author-email: almar.klein@gmail.com
License: GPL-3.0
Classifier: Development Status :: 5 - Production/Stable
Classifier: Intended Audience :: Developers
Classifier: License :: OSI Approved :: GNU General Public License v3 (GPLv3)
Classifier: Operating System :: MacOS :: MacOS X
Classifier: Operating System :: Microsoft :: Windows
Classifier: Operating System :: POSIX
Classifier: Programming Language :: Python
Classifier: Programming Language :: Python :: 3 :: Only
Classifier: Programming Language :: Python :: 3.9
Classifier: Programming Language :: Python :: 3.10
Classifier: Programming Language :: Python :: 3.11
Classifier: Programming Language :: Python :: 3.12
Classifier: Programming Language :: Python :: 3.13
Requires-Python: >=3.6.0
License-File: LICENSE
Requires-Dist: uvicorn
Requires-Dist: asgineer>=0.8.0
Requires-Dist: itemdb>=1.1.1
Requires-Dist: pscript>=0.7.6
Requires-Dist: pyjwt
Requires-Dist: jinja2
Requires-Dist: markdown
Requires-Dist: bcrypt
Requires-Dist: iptools
Dynamic: author
Dynamic: author-email
Dynamic: classifier
Dynamic: description
Dynamic: description-content-type
Dynamic: home-page
Dynamic: license
Dynamic: license-file
Dynamic: requires-dist
Dynamic: requires-python
Dynamic: summary
